email_views/__init__.py
django_email_views-0.1.dist-info/LICENSE
django_email_views-0.1.dist-info/METADATA
django_email_views-0.1.dist-info/WHEEL
django_email_views-0.1.dist-info/top_level.txt
django_email_views-0.1.dist-info/RECORD
